llconfig/__init__.py
llconfig/converters.py
llconfig-2.0.1.dist-info/LICENSE
llconfig-2.0.1.dist-info/METADATA
llconfig-2.0.1.dist-info/WHEEL
llconfig-2.0.1.dist-info/top_level.txt
llconfig-2.0.1.dist-info/RECORD
