Metadata-Version: 2.1
Name: llconfig
Version: 2.0.1
Summary: Lightweight layered configuration library.
Home-page: https://github.com/heureka/llconfig
Author: Heureka.cz
Author-email: vyvoj@heureka.cz
License: Apache 2.0
Platform: UNKNOWN
License-File: LICENSE
